canonicalwebteam/__init__.py
canonicalwebteam/custom_response_headers/__init__.py
canonicalwebteam.custom_response_headers-0.2.0.dist-info/LICENSE.txt
canonicalwebteam.custom_response_headers-0.2.0.dist-info/METADATA
canonicalwebteam.custom_response_headers-0.2.0.dist-info/WHEEL
canonicalwebteam.custom_response_headers-0.2.0.dist-info/top_level.txt
canonicalwebteam.custom_response_headers-0.2.0.dist-info/RECORD
