Metadata-Version: 2.1
Name: canonicalwebteam.custom-response-headers
Version: 0.2.0
Summary: Django middleware for setting custom HTTP headersto be included in every HTTP response.
Home-page: https://github.com/canonical-webteam/custom-response-headers
Author: Canonical Webteam
License: UNKNOWN
Platform: UNKNOWN
Requires-Dist: Django (>=1.3)
